groheblue/__init__.py
groheblue/classes.py
groheblue/client.py
groheblue/controller.py
groheblue/tokens.py
groheblue/utils.py
groheblue-0.3.2.dist-info/LICENSE
groheblue-0.3.2.dist-info/METADATA
groheblue-0.3.2.dist-info/WHEEL
groheblue-0.3.2.dist-info/top_level.txt
groheblue-0.3.2.dist-info/RECORD
