Metadata-Version: 2.1
Name: groheblue
Version: 0.3.2
Summary: A python package for interacting with the Grohe Blue API.
Home-page: https://github.com/koproductions-code/groheblue
Author: Konstantin Weber
License: MIT
Project-URL: GitHub, https://github.com/koproductions-code/groheblue
Requires-Python: >=3.6
License-File: LICENSE
Requires-Dist: bs4==0.0.2
Requires-Dist: httpx>=0.27.0
